{"__TABLE_DEFINITION": {"name": "LoginRecordTable", "factor": 1, "frozen": false, "schema": {"type": "object", "x-zui": {}, "properties": {"user_id": {"type": "number", "x-zui": {"index": 0, "searchable": true}, "nullable": true}}, "additionalProperties": true}, "tags": {}, "keyColumn": null, "isComputeEnabled": false, "createdAt": "2026-03-22T14:04:05.036Z", "updatedAt": "2026-03-22T14:14:36.118Z", "rowsCount": 55}}
{"computed": {}, "stale": [], "id": 4, "createdAt": "2026-03-22T14:14:15", "updatedAt": "2026-03-22T14:14:39", "user_id": 1}
{"computed": {}, "stale": [], "id": 5, "createdAt": "2026-03-22T15:00:37", "updatedAt": "2026-03-22T15:00:37", "user_id": 4}
{"computed": {}, "stale": [], "id": 6, "createdAt": "2026-03-22T15:04:22", "updatedAt": "2026-03-22T15:04:22", "user_id": 4}
{"computed": {}, "stale": [], "id": 7, "createdAt": "2026-03-22T15:13:17", "updatedAt": "2026-03-22T15:13:17", "user_id": 4}
{"computed": {}, "stale": [], "id": 8, "createdAt": "2026-03-22T15:14:44", "updatedAt": "2026-03-22T15:14:44", "user_id": 4}
{"computed": {}, "stale": [], "id": 9, "createdAt": "2026-03-22T15:17:07", "updatedAt": "2026-03-22T15:17:07", "user_id": 4}
{"computed": {}, "stale": [], "id": 10, "createdAt": "2026-03-22T15:20:34", "updatedAt": "2026-03-22T15:20:34", "user_id": 4}
{"computed": {}, "stale": [], "id": 11, "createdAt": "2026-03-22T15:21:27", "updatedAt": "2026-03-22T15:21:27", "user_id": 4}
{"computed": {}, "stale": [], "id": 12, "createdAt": "2026-03-22T15:23:17", "updatedAt": "2026-03-22T15:23:17", "user_id": 4}
{"computed": {}, "stale": [], "id": 13, "createdAt": "2026-03-22T15:39:31", "updatedAt": "2026-03-22T15:39:31", "user_id": 4}
{"computed": {}, "stale": [], "id": 14, "createdAt": "2026-03-22T15:42:05", "updatedAt": "2026-03-22T15:42:05", "user_id": 4}
{"computed": {}, "stale": [], "id": 15, "createdAt": "2026-03-22T15:50:35", "updatedAt": "2026-03-22T15:50:35", "user_id": 4}
{"computed": {}, "stale": [], "id": 16, "createdAt": "2026-03-22T15:52:43", "updatedAt": "2026-03-22T15:52:43", "user_id": 4}
{"computed": {}, "stale": [], "id": 17, "createdAt": "2026-03-22T15:56:06", "updatedAt": "2026-03-22T15:56:06", "user_id": 4}
{"computed": {}, "stale": [], "id": 18, "createdAt": "2026-03-22T16:01:04", "updatedAt": "2026-03-22T16:01:04", "user_id": 4}
{"computed": {}, "stale": [], "id": 19, "createdAt": "2026-03-22T16:04:12", "updatedAt": "2026-03-22T16:04:12", "user_id": 4}
{"computed": {}, "stale": [], "id": 20, "createdAt": "2026-03-22T16:07:22", "updatedAt": "2026-03-22T16:07:22", "user_id": 4}
{"computed": {}, "stale": [], "id": 21, "createdAt": "2026-03-22T16:10:35", "updatedAt": "2026-03-22T16:10:35", "user_id": 4}
{"computed": {}, "stale": [], "id": 22, "createdAt": "2026-03-22T16:13:17", "updatedAt": "2026-03-22T16:13:17", "user_id": 4}
{"computed": {}, "stale": [], "id": 23, "createdAt": "2026-03-22T16:15:16", "updatedAt": "2026-03-22T16:15:16", "user_id": 4}
{"computed": {}, "stale": [], "id": 24, "createdAt": "2026-03-22T16:43:49", "updatedAt": "2026-03-22T16:43:49", "user_id": 4}
{"computed": {}, "stale": [], "id": 25, "createdAt": "2026-03-22T17:25:31", "updatedAt": "2026-03-22T17:25:31", "user_id": 0}
{"computed": {}, "stale": [], "id": 26, "createdAt": "2026-03-22T17:27:40", "updatedAt": "2026-03-22T17:27:40", "user_id": -1}
{"computed": {}, "stale": [], "id": 27, "createdAt": "2026-03-22T17:29:33", "updatedAt": "2026-03-22T17:29:33", "user_id": 4}
{"computed": {}, "stale": [], "id": 28, "createdAt": "2026-03-22T17:35:06", "updatedAt": "2026-03-22T17:35:06", "user_id": 4}
{"computed": {}, "stale": [], "id": 29, "createdAt": "2026-03-22T17:36:30", "updatedAt": "2026-03-22T17:36:30", "user_id": 4}
{"computed": {}, "stale": [], "id": 30, "createdAt": "2026-03-22T17:37:33", "updatedAt": "2026-03-22T17:37:33", "user_id": 4}
{"computed": {}, "stale": [], "id": 31, "createdAt": "2026-03-22T17:40:18", "updatedAt": "2026-03-22T17:40:18", "user_id": 4}
{"computed": {}, "stale": [], "id": 32, "createdAt": "2026-03-23T02:40:12", "updatedAt": "2026-03-23T02:40:12", "user_id": 1}
{"computed": {}, "stale": [], "id": 33, "createdAt": "2026-03-23T07:04:25", "updatedAt": "2026-03-23T07:04:25", "user_id": 4}
{"computed": {}, "stale": [], "id": 34, "createdAt": "2026-03-23T07:08:22", "updatedAt": "2026-03-23T07:08:22", "user_id": 4}
{"computed": {}, "stale": [], "id": 35, "createdAt": "2026-03-23T07:10:16", "updatedAt": "2026-03-23T07:10:16", "user_id": 4}
{"computed": {}, "stale": [], "id": 36, "createdAt": "2026-03-23T07:11:03", "updatedAt": "2026-03-23T07:11:03", "user_id": 4}
{"computed": {}, "stale": [], "id": 37, "createdAt": "2026-03-23T07:13:13", "updatedAt": "2026-03-23T07:13:13", "user_id": 4}
{"computed": {}, "stale": [], "id": 38, "createdAt": "2026-03-23T07:14:11", "updatedAt": "2026-03-23T07:14:11", "user_id": 4}
{"computed": {}, "stale": [], "id": 39, "createdAt": "2026-03-23T07:14:56", "updatedAt": "2026-03-23T07:14:56", "user_id": 4}
{"computed": {}, "stale": [], "id": 40, "createdAt": "2026-03-23T07:16:16", "updatedAt": "2026-03-23T07:16:16", "user_id": 4}
{"computed": {}, "stale": [], "id": 41, "createdAt": "2026-03-23T07:17:58", "updatedAt": "2026-03-23T07:17:58", "user_id": 4}
{"computed": {}, "stale": [], "id": 42, "createdAt": "2026-03-23T07:19:05", "updatedAt": "2026-03-23T07:19:05", "user_id": 4}
{"computed": {}, "stale": [], "id": 43, "createdAt": "2026-03-23T07:20:28", "updatedAt": "2026-03-23T07:20:28", "user_id": 4}
{"computed": {}, "stale": [], "id": 44, "createdAt": "2026-03-23T07:23:41", "updatedAt": "2026-03-23T07:23:41", "user_id": 4}
{"computed": {}, "stale": [], "id": 45, "createdAt": "2026-03-23T07:26:54", "updatedAt": "2026-03-23T07:26:54", "user_id": 6}
{"computed": {}, "stale": [], "id": 46, "createdAt": "2026-03-23T07:36:08", "updatedAt": "2026-03-23T07:36:08", "user_id": 4}
{"computed": {}, "stale": [], "id": 47, "createdAt": "2026-03-23T07:47:29", "updatedAt": "2026-03-23T07:47:29", "user_id": 4}
{"computed": {}, "stale": [], "id": 48, "createdAt": "2026-03-23T07:48:57", "updatedAt": "2026-03-23T07:48:57", "user_id": 4}
{"computed": {}, "stale": [], "id": 49, "createdAt": "2026-03-23T07:55:05", "updatedAt": "2026-03-23T07:55:05", "user_id": 5}
{"computed": {}, "stale": [], "id": 50, "createdAt": "2026-03-23T07:58:10", "updatedAt": "2026-03-23T07:58:10", "user_id": 4}
{"computed": {}, "stale": [], "id": 51, "createdAt": "2026-03-23T14:25:15", "updatedAt": "2026-03-23T14:25:15", "user_id": 4}
{"computed": {}, "stale": [], "id": 52, "createdAt": "2026-03-23T15:31:41", "updatedAt": "2026-03-23T15:31:41", "user_id": 4}
{"computed": {}, "stale": [], "id": 53, "createdAt": "2026-03-23T15:41:36", "updatedAt": "2026-03-23T15:41:36", "user_id": 4}
{"computed": {}, "stale": [], "id": 54, "createdAt": "2026-03-26T11:53:30", "updatedAt": "2026-03-26T11:53:30", "user_id": 1}
{"computed": {}, "stale": [], "id": 55, "createdAt": "2026-03-26T12:06:22", "updatedAt": "2026-03-26T12:06:22", "user_id": 1}
{"computed": {}, "stale": [], "id": 56, "createdAt": "2026-03-26T12:08:09", "updatedAt": "2026-03-26T12:08:09", "user_id": 1}
{"computed": {}, "stale": [], "id": 57, "createdAt": "2026-03-26T12:19:32", "updatedAt": "2026-03-26T12:19:32", "user_id": 1}
{"computed": {}, "stale": [], "id": 58, "createdAt": "2026-03-26T12:20:16", "updatedAt": "2026-03-26T12:20:16", "user_id": 1}
{"computed": {}, "stale": [], "id": 59, "createdAt": "2026-03-31T00:13:45", "updatedAt": "2026-03-31T00:13:45", "user_id": 4}
{"computed": {}, "stale": [], "id": 60, "createdAt": "2026-04-04T10:56:40", "updatedAt": "2026-04-04T10:56:40", "user_id": 1}
{"computed": {}, "stale": [], "id": 61, "createdAt": "2026-04-04T11:01:05", "updatedAt": "2026-04-04T11:01:05", "user_id": 1}
{"computed": {}, "stale": [], "id": 62, "createdAt": "2026-04-04T11:05:00", "updatedAt": "2026-04-04T11:05:00", "user_id": 1}
{"computed": {}, "stale": [], "id": 63, "createdAt": "2026-04-04T11:05:31", "updatedAt": "2026-04-04T11:05:31", "user_id": 1}
{"computed": {}, "stale": [], "id": 64, "createdAt": "2026-04-04T11:06:50", "updatedAt": "2026-04-04T11:06:50", "user_id": 1}
{"computed": {}, "stale": [], "id": 65, "createdAt": "2026-04-04T11:12:12", "updatedAt": "2026-04-04T11:12:12", "user_id": 1}
{"computed": {}, "stale": [], "id": 66, "createdAt": "2026-04-04T11:13:36", "updatedAt": "2026-04-04T11:13:36", "user_id": 1}
{"computed": {}, "stale": [], "id": 67, "createdAt": "2026-04-04T11:18:58", "updatedAt": "2026-04-04T11:18:58", "user_id": 1}
{"computed": {}, "stale": [], "id": 68, "createdAt": "2026-04-04T11:21:51", "updatedAt": "2026-04-04T11:21:51", "user_id": 1}
{"computed": {}, "stale": [], "id": 69, "createdAt": "2026-04-04T11:27:06", "updatedAt": "2026-04-04T11:27:06", "user_id": 1}
{"computed": {}, "stale": [], "id": 70, "createdAt": "2026-04-04T11:28:08", "updatedAt": "2026-04-04T11:28:08", "user_id": 1}
{"computed": {}, "stale": [], "id": 71, "createdAt": "2026-04-04T11:31:46", "updatedAt": "2026-04-04T11:31:46", "user_id": 1}
{"computed": {}, "stale": [], "id": 72, "createdAt": "2026-04-04T11:35:13", "updatedAt": "2026-04-04T11:35:13", "user_id": 1}
{"computed": {}, "stale": [], "id": 73, "createdAt": "2026-04-04T11:36:11", "updatedAt": "2026-04-04T11:36:11", "user_id": 1}
{"computed": {}, "stale": [], "id": 74, "createdAt": "2026-04-04T11:38:00", "updatedAt": "2026-04-04T11:38:00", "user_id": 1}
{"computed": {}, "stale": [], "id": 75, "createdAt": "2026-04-04T11:46:20", "updatedAt": "2026-04-04T11:46:20", "user_id": 1}
{"computed": {}, "stale": [], "id": 76, "createdAt": "2026-04-04T11:49:22", "updatedAt": "2026-04-04T11:49:22", "user_id": 1}
{"computed": {}, "stale": [], "id": 77, "createdAt": "2026-04-04T12:20:00", "updatedAt": "2026-04-04T12:20:00", "user_id": 1}
{"computed": {}, "stale": [], "id": 78, "createdAt": "2026-04-04T17:17:06", "updatedAt": "2026-04-04T17:17:06", "user_id": 1}
{"computed": {}, "stale": [], "id": 79, "createdAt": "2026-04-04T17:18:47", "updatedAt": "2026-04-04T17:18:47", "user_id": 1}
{"computed": {}, "stale": [], "id": 80, "createdAt": "2026-04-04T17:21:09", "updatedAt": "2026-04-04T17:21:09", "user_id": 1}
{"computed": {}, "stale": [], "id": 81, "createdAt": "2026-04-04T17:23:48", "updatedAt": "2026-04-04T17:23:48", "user_id": 1}
{"computed": {}, "stale": [], "id": 82, "createdAt": "2026-04-04T17:24:28", "updatedAt": "2026-04-04T17:24:28", "user_id": 1}
{"computed": {}, "stale": [], "id": 83, "createdAt": "2026-04-04T17:41:22", "updatedAt": "2026-04-04T17:41:22", "user_id": 1}
{"computed": {}, "stale": [], "id": 84, "createdAt": "2026-04-04T17:42:40", "updatedAt": "2026-04-04T17:42:40", "user_id": 1}
{"computed": {}, "stale": [], "id": 85, "createdAt": "2026-04-04T17:43:28", "updatedAt": "2026-04-04T17:43:28", "user_id": 1}
{"computed": {}, "stale": [], "id": 86, "createdAt": "2026-04-04T17:50:45", "updatedAt": "2026-04-04T17:50:45", "user_id": 1}
{"computed": {}, "stale": [], "id": 87, "createdAt": "2026-04-04T17:51:45", "updatedAt": "2026-04-04T17:51:45", "user_id": 1}
{"computed": {}, "stale": [], "id": 88, "createdAt": "2026-04-04T17:53:16", "updatedAt": "2026-04-04T17:53:16", "user_id": 1}
{"computed": {}, "stale": [], "id": 89, "createdAt": "2026-04-04T17:54:04", "updatedAt": "2026-04-04T17:54:04", "user_id": 1}
{"computed": {}, "stale": [], "id": 90, "createdAt": "2026-04-04T17:54:34", "updatedAt": "2026-04-04T17:54:34", "user_id": 1}
{"computed": {}, "stale": [], "id": 91, "createdAt": "2026-04-04T17:55:06", "updatedAt": "2026-04-04T17:55:06", "user_id": 1}
{"computed": {}, "stale": [], "id": 92, "createdAt": "2026-04-08T00:56:31", "updatedAt": "2026-04-08T00:56:31", "user_id": 1}
{"computed": {}, "stale": [], "id": 93, "createdAt": "2026-04-08T02:58:53", "updatedAt": "2026-04-08T02:58:53", "user_id": 1}
{"computed": {}, "stale": [], "id": 94, "createdAt": "2026-04-08T03:41:49", "updatedAt": "2026-04-08T03:41:49", "user_id": 1}
{"computed": {}, "stale": [], "id": 95, "createdAt": "2026-04-08T03:42:37", "updatedAt": "2026-04-08T03:42:37", "user_id": 1}
{"computed": {}, "stale": [], "id": 96, "createdAt": "2026-04-08T03:46:52", "updatedAt": "2026-04-08T03:46:52", "user_id": 1}
{"computed": {}, "stale": [], "id": 97, "createdAt": "2026-04-08T03:49:55", "updatedAt": "2026-04-08T03:49:55", "user_id": 1}
{"computed": {}, "stale": [], "id": 98, "createdAt": "2026-04-08T03:52:18", "updatedAt": "2026-04-08T03:52:18", "user_id": 1}
{"computed": {}, "stale": [], "id": 99, "createdAt": "2026-04-08T03:53:19", "updatedAt": "2026-04-08T03:53:19", "user_id": 1}
{"computed": {}, "stale": [], "id": 100, "createdAt": "2026-04-08T03:55:10", "updatedAt": "2026-04-08T03:55:10", "user_id": 1}
{"computed": {}, "stale": [], "id": 101, "createdAt": "2026-04-08T21:51:56", "updatedAt": "2026-04-08T21:51:56", "user_id": 1}
{"computed": {}, "stale": [], "id": 102, "createdAt": "2026-04-08T21:52:33", "updatedAt": "2026-04-08T21:52:33", "user_id": 1}
{"computed": {}, "stale": [], "id": 103, "createdAt": "2026-04-08T21:56:09", "updatedAt": "2026-04-08T21:56:09", "user_id": 1}
{"computed": {}, "stale": [], "id": 104, "createdAt": "2026-04-08T22:16:08", "updatedAt": "2026-04-08T22:16:08", "user_id": 1}
{"computed": {}, "stale": [], "id": 105, "createdAt": "2026-04-08T22:27:58", "updatedAt": "2026-04-08T22:27:58", "user_id": 1}
{"computed": {}, "stale": [], "id": 106, "createdAt": "2026-04-08T22:30:01", "updatedAt": "2026-04-08T22:30:01", "user_id": 1}
{"computed": {}, "stale": [], "id": 107, "createdAt": "2026-04-08T22:32:00", "updatedAt": "2026-04-08T22:32:00", "user_id": 1}
{"computed": {}, "stale": [], "id": 108, "createdAt": "2026-04-08T22:33:24", "updatedAt": "2026-04-08T22:33:24", "user_id": 1}
{"computed": {}, "stale": [], "id": 109, "createdAt": "2026-04-08T22:35:15", "updatedAt": "2026-04-08T22:35:15", "user_id": 1}
{"computed": {}, "stale": [], "id": 110, "createdAt": "2026-04-08T22:36:04", "updatedAt": "2026-04-08T22:36:04", "user_id": 1}
{"computed": {}, "stale": [], "id": 111, "createdAt": "2026-04-08T22:38:47", "updatedAt": "2026-04-08T22:38:47", "user_id": 1}
{"computed": {}, "stale": [], "id": 112, "createdAt": "2026-04-08T22:42:52", "updatedAt": "2026-04-08T22:42:52", "user_id": 1}
{"computed": {}, "stale": [], "id": 113, "createdAt": "2026-04-08T22:46:34", "updatedAt": "2026-04-08T22:46:34", "user_id": 1}
{"computed": {}, "stale": [], "id": 114, "createdAt": "2026-04-10T19:40:32", "updatedAt": "2026-04-10T19:40:32", "user_id": 1}
{"computed": {}, "stale": [], "id": 115, "createdAt": "2026-04-10T19:46:26", "updatedAt": "2026-04-10T19:46:26", "user_id": 1}
{"computed": {}, "stale": [], "id": 116, "createdAt": "2026-04-10T19:51:25", "updatedAt": "2026-04-10T19:51:25", "user_id": 1}
{"computed": {}, "stale": [], "id": 117, "createdAt": "2026-04-10T19:53:19", "updatedAt": "2026-04-10T19:53:19", "user_id": 1}
